slg_file_operations/__init__.py
slg_file_operations/file_operations.py
slg_file_operations-1.0.1.data/scripts/slg-file-operations
slg_file_operations-1.0.1.dist-info/METADATA
slg_file_operations-1.0.1.dist-info/WHEEL
slg_file_operations-1.0.1.dist-info/top_level.txt
slg_file_operations-1.0.1.dist-info/RECORD
